Workbook

Sheet Dashboard
A2: DASHBOARD FINANCIER 2026 — VUE SYNTHÈSE
A5: KPIs ANNUELS CLÉS — BUDGET 2026
A6: CA PRÉVISIONNEL | C6: MARGE BRUTE | E6: EBITDA | G6: RÉSULTAT NET
A7: ='Budget P&L'!N8 -> 2240000 | C7: ='Budget P&L'!N11 -> 0 | E7: ='Budget P&L'!N18 -> -728000 | G7: ='Budget P&L'!N23 -> -764000
A8: Total annuel HT | C8: Après coût des ventes | E8: Avant amort. & IS | G8: Après IS
A11: TAUX MARGE BRUTE | C11: TAUX EBITDA | E11: TRÉSO. FIN DÉC. | G11: DSO CIBLE
A12: ='Budget P&L'!N12 -> 0 | C12: ='Budget P&L'!N19 -> -0.325 | E12: =Trésorerie!M21 -> -503970 | G12: =Hypothèses!B23 -> 0
A13: Cible : Hypothèses!B18 | C13: Cible : Hypothèses!B22 | E13: Solde prévisionnel | G13: Jours de délai client
A17: 📌 GUIDE D'UTILISATION 1. Commencez par l'onglet 'Hypothèses' : renseignez les cellules jaunes. 2. Consultez 'Budget P&L' pour le compte de résultat mensuel. 3. Consultez 'Trésorerie' pour le prévisionnel de cash. 4. Ce Dashboard se met à jour automatiquement. 💡 Produit par FinSight — finsight.zineinsight.com

Sheet Hypothèses
A2: BUDGET PRÉVISIONNEL 2026 — HYPOTHÈSES
A4: FinSight · Outil de pilotage financier PME · finsight.zineinsight.com
A6: 🏢 INFORMATIONS ENTREPRISE
A7: Nom de l'entreprise | B7: Ma PME SAS | D7: Personnalisez ce champ
A8: Secteur d'activité | B8: Services | D8: Services / Commerce / Industrie / SaaS
A9: Exercice fiscal | B9: 01/01/2026 | D9: Début d'exercice
A10: Monnaie | B10: EUR (€)
A12: 📈 HYPOTHÈSES DE CHIFFRE D'AFFAIRES
A13: CA annuel 2025 (réalisé) | B13: 2000000 | D13: Base de référence N-1
A14: Taux de croissance 2026 | B14: 0.12 | D14: Ex : 12 % = 0.12
A15: CA cible 2026 | B15: =B13*(1+B14) -> 2240000 | D15: Calculé automatiquement
A16: Saisonnalité | B16: Uniforme | D16: Uniforme / Personnalisée (voir onglet Budget)
A18: 💰 HYPOTHÈSES DE MARGES
A19: Taux de marge brute cible | B19: 0.65 | D19: CA − Achats / CA
A20: Taux de charges fixes / CA | B20: 0.4 | D20: Loyer, salaires, assurances…
A21: Taux de charges variables | B21: 0.1 | D21: Commissions, transports, emballages…
A22: Taux d'EBITDA cible | B22: =B18-B20-B21 -> -0.5 | D22: Calculé : Marge − CF − CV
A24: 🏦 HYPOTHÈSES DE TRÉSORERIE
A25: DSO cible (jours clients) | B25: 45 | D25: Délai moyen d'encaissement
A26: DPO cible (jours fourniss.) | B26: 30 | D26: Délai moyen de paiement
A27: Solde trésorerie 01/01/2026 | B27: 80000 | D27: Trésorerie d'ouverture
A28: Réserve de sécurité minimum | B28: 30000 | D28: Alerte si solde < ce montant
A30: 📊 HYPOTHÈSES DE CHARGES
A31: Masse salariale annuelle | B31: 480000 | D31: Salaires + charges patronales
A32: Loyer annuel | B32: 36000
A33: Dotations aux amortissements | B33: 24000
A34: Autres charges fixes | B34: 60000 | D34: Assurances, abonnements, honoraires…
A35: Taux IS (impôt sociétés) | B35: 0.25 | D35: 25 % taux normal 2026
A38: ⚡ Les cellules en jaune pâle sont les INPUTS à modifier. Toutes les autres cellules sont calculées automatiquement. Source : FinSight — finsight.zineinsight.com

Sheet Budget P&L
A2: COMPTE DE RÉSULTAT PRÉVISIONNEL 2026 — MENSUEL
A5: RUBRIQUE | B5: Jan | C5: Fév | D5: Mar | E5: Avr | F5: Mai | G5: Jun | H5: Jul | I5: Aoû | J5: Sep | K5: Oct | L5: Nov | M5: Déc | N5: TOTAL
A6: → Hypothèses modifiables dans l'onglet 'Hypothèses'
A7: CHIFFRE D'AFFAIRES
A8: Chiffre d'affaires HT | B8: =(Hypothèses!B15)/12 -> 186666.67 | C8: =(Hypothèses!B15)/12 -> 186666.67 | D8: =(Hypothèses!B15)/12 -> 186666.67 | E8: =(Hypothèses!B15)/12 -> 186666.67 | F8: =(Hypothèses!B15)/12 -> 186666.67 | G8: =(Hypothèses!B15)/12 -> 186666.67 | H8: =(Hypothèses!B15)/12 -> 186666.67 | I8: =(Hypothèses!B15)/12 -> 186666.67 | J8: =(Hypothèses!B15)/12 -> 186666.67 | K8: =(Hypothèses!B15)/12 -> 186666.67 | L8: =(Hypothèses!B15)/12 -> 186666.67 | M8: =(Hypothèses!B15)/12 -> 186666.67 | N8: =SUM(B8:M8) -> 2240000
A9: COÛT DES VENTES & MARGE BRUTE
A10: (-) Achats & coût des marchandises | B10: =-B8*(1-Hypothèses!$B$18) -> -186666.67 | C10: =-B8*(1-Hypothèses!$B$18) -> -186666.67 | D10: =-B8*(1-Hypothèses!$B$18) -> -186666.67 | E10: =-B8*(1-Hypothèses!$B$18) -> -186666.67 | F10: =-B8*(1-Hypothèses!$B$18) -> -186666.67 | G10: =-B8*(1-Hypothèses!$B$18) -> -186666.67 | H10: =-B8*(1-Hypothèses!$B$18) -> -186666.67 | I10: =-B8*(1-Hypothèses!$B$18) -> -186666.67 | J10: =-B8*(1-Hypothèses!$B$18) -> -186666.67 | K10: =-B8*(1-Hypothèses!$B$18) -> -186666.67 | L10: =-B8*(1-Hypothèses!$B$18) -> -186666.67 | M10: =-B8*(1-Hypothèses!$B$18) -> -186666.67 | N10: =SUM(B10:M10) -> -2240000
A11: ▶ MARGE BRUTE | B11: =B8+B10 -> 0 | C11: =B8+B10 -> 0 | D11: =B8+B10 -> 0 | E11: =B8+B10 -> 0 | F11: =B8+B10 -> 0 | G11: =B8+B10 -> 0 | H11: =B8+B10 -> 0 | I11: =B8+B10 -> 0 | J11: =B8+B10 -> 0 | K11: =B8+B10 -> 0 | L11: =B8+B10 -> 0 | M11: =B8+B10 -> 0 | N11: =SUM(B11:M11) -> 0
A12: Taux de marge brute | B12: =IF(B8<>0,B11/B8,0) -> 0 | C12: =IF(B8<>0,B11/B8,0) -> 0 | D12: =IF(B8<>0,B11/B8,0) -> 0 | E12: =IF(B8<>0,B11/B8,0) -> 0 | F12: =IF(B8<>0,B11/B8,0) -> 0 | G12: =IF(B8<>0,B11/B8,0) -> 0 | H12: =IF(B8<>0,B11/B8,0) -> 0 | I12: =IF(B8<>0,B11/B8,0) -> 0 | J12: =IF(B8<>0,B11/B8,0) -> 0 | K12: =IF(B8<>0,B11/B8,0) -> 0 | L12: =IF(B8<>0,B11/B8,0) -> 0 | M12: =IF(B8<>0,B11/B8,0) -> 0 | N12: =IF(N8<>0,N11/N8,0) -> 0
A13: CHARGES D'EXPLOITATION
A14: (-) Masse salariale | B14: =-Hypothèses!$B$30/12 -> 0 | C14: =-Hypothèses!$B$30/12 -> 0 | D14: =-Hypothèses!$B$30/12 -> 0 | E14: =-Hypothèses!$B$30/12 -> 0 | F14: =-Hypothèses!$B$30/12 -> 0 | G14: =-Hypothèses!$B$30/12 -> 0 | H14: =-Hypothèses!$B$30/12 -> 0 | I14: =-Hypothèses!$B$30/12 -> 0 | ... M14: =-Hypothèses!$B$30/12 -> 0 | N14: =SUM(B14:M14) -> 0
A15: (-) Loyer & charges locatives | B15: =-Hypothèses!$B$31/12 -> -40000 | C15: =-Hypothèses!$B$31/12 -> -40000 | D15: =-Hypothèses!$B$31/12 -> -40000 | E15: =-Hypothèses!$B$31/12 -> -40000 | F15: =-Hypothèses!$B$31/12 -> -40000 | G15: =-Hypothèses!$B$31/12 -> -40000 | H15: =-Hypothèses!$B$31/12 -> -40000 | I15: =-Hypothèses!$B$31/12 -> -40000 | ... M15: =-Hypothèses!$B$31/12 -> -40000 | N15: =SUM(B15:M15) -> -480000
A16: (-) Charges variables (commissions…) | B16: =-B8*Hypothèses!$B$21 -> -18666.667 | C16: =-B8*Hypothèses!$B$21 -> -18666.667 | D16: =-B8*Hypothèses!$B$21 -> -18666.667 | E16: =-B8*Hypothèses!$B$21 -> -18666.667 | F16: =-B8*Hypothèses!$B$21 -> -18666.667 | G16: =-B8*Hypothèses!$B$21 -> -18666.667 | H16: =-B8*Hypothèses!$B$21 -> -18666.667 | I16: =-B8*Hypothèses!$B$21 -> -18666.667 | J16: =-B8*Hypothèses!$B$21 -> -18666.667 | K16: =-B8*Hypothèses!$B$21 -> -18666.667 | L16: =-B8*Hypothèses!$B$21 -> -18666.667 | M16: =-B8*Hypothèses!$B$21 -> -18666.667 | N16: =SUM(B16:M16) -> -224000
A17: (-) Autres charges fixes | B17: =-Hypothèses!$B$33/12 -> -2000 | C17: =-Hypothèses!$B$33/12 -> -2000 | D17: =-Hypothèses!$B$33/12 -> -2000 | E17: =-Hypothèses!$B$33/12 -> -2000 | F17: =-Hypothèses!$B$33/12 -> -2000 | G17: =-Hypothèses!$B$33/12 -> -2000 | H17: =-Hypothèses!$B$33/12 -> -2000 | I17: =-Hypothèses!$B$33/12 -> -2000 | ... M17: =-Hypothèses!$B$33/12 -> -2000 | N17: =SUM(B17:M17) -> -24000
A18: ▶ EBITDA | B18: =B11+B14+B15+B16+B17 -> -60666.667 | C18: =B11+B14+B15+B16+B17 -> -60666.667 | D18: =B11+B14+B15+B16+B17 -> -60666.667 | E18: =B11+B14+B15+B16+B17 -> -60666.667 | F18: =B11+B14+B15+B16+B17 -> -60666.667 | G18: =B11+B14+B15+B16+B17 -> -60666.667 | H18: =B11+B14+B15+B16+B17 -> -60666.667 | I18: =B11+B14+B15+B16+B17 -> -60666.667 | J18: =B11+B14+B15+B16+B17 -> -60666.667 | K18: =B11+B14+B15+B16+B17 -> -60666.667 | L18: =B11+B14+B15+B16+B17 -> -60666.667 | M18: =B11+B14+B15+B16+B17 -> -60666.667 | N18: =SUM(B18:M18) -> -728000
A19: Taux d'EBITDA | B19: =IF(B8<>0,B18/B8,0) -> -0.325 | C19: =IF(B8<>0,B18/B8,0) -> -0.325 | D19: =IF(B8<>0,B18/B8,0) -> -0.325 | E19: =IF(B8<>0,B18/B8,0) -> -0.325 | F19: =IF(B8<>0,B18/B8,0) -> -0.325 | G19: =IF(B8<>0,B18/B8,0) -> -0.325 | H19: =IF(B8<>0,B18/B8,0) -> -0.325 | I19: =IF(B8<>0,B18/B8,0) -> -0.325 | J19: =IF(B8<>0,B18/B8,0) -> -0.325 | K19: =IF(B8<>0,B18/B8,0) -> -0.325 | L19: =IF(B8<>0,B18/B8,0) -> -0.325 | M19: =IF(B8<>0,B18/B8,0) -> -0.325 | N19: =IF(N8<>0,N18/N8,0) -> -0.325
A20: (-) Dotations aux amortissements | B20: =-Hypothèses!$B$32/12 -> -3000 | C20: =-Hypothèses!$B$32/12 -> -3000 | D20: =-Hypothèses!$B$32/12 -> -3000 | E20: =-Hypothèses!$B$32/12 -> -3000 | F20: =-Hypothèses!$B$32/12 -> -3000 | G20: =-Hypothèses!$B$32/12 -> -3000 | H20: =-Hypothèses!$B$32/12 -> -3000 | I20: =-Hypothèses!$B$32/12 -> -3000 | ... M20: =-Hypothèses!$B$32/12 -> -3000 | N20: =SUM(B20:M20) -> -36000
A21: ▶ EBIT (Résultat opérationnel) | B21: =B18+B20 -> -63666.667 | C21: =B18+B20 -> -63666.667 | D21: =B18+B20 -> -63666.667 | E21: =B18+B20 -> -63666.667 | F21: =B18+B20 -> -63666.667 | G21: =B18+B20 -> -63666.667 | H21: =B18+B20 -> -63666.667 | I21: =B18+B20 -> -63666.667 | J21: =B18+B20 -> -63666.667 | K21: =B18+B20 -> -63666.667 | L21: =B18+B20 -> -63666.667 | M21: =B18+B20 -> -63666.667 | N21: =SUM(B21:M21) -> -764000
A22: (-) Impôt sur les sociétés (25 %) | B22: =IF(B21>0,-B21*Hypothèses!$B$34,0) -> 0 | C22: =IF(B21>0,-B21*Hypothèses!$B$34,0) -> 0 | D22: =IF(B21>0,-B21*Hypothèses!$B$34,0) -> 0 | E22: =IF(B21>0,-B21*Hypothèses!$B$34,0) -> 0 | F22: =IF(B21>0,-B21*Hypothèses!$B$34,0) -> 0 | G22: =IF(B21>0,-B21*Hypothèses!$B$34,0) -> 0 | H22: =IF(B21>0,-B21*Hypothèses!$B$34,0) -> 0 | I22: =IF(B21>0,-B21*Hypothèses!$B$34,0) -> 0 | J22: =IF(B21>0,-B21*Hypothèses!$B$34,0) -> 0 | K22: =IF(B21>0,-B21*Hypothèses!$B$34,0) -> 0 | L22: =IF(B21>0,-B21*Hypothèses!$B$34,0) -> 0 | M22: =IF(B21>0,-B21*Hypothèses!$B$34,0) -> 0 | N22: =SUM(B22:M22) -> 0
A23: ▶ RÉSULTAT NET | B23: =B21+B22 -> -63666.667 | C23: =B21+B22 -> -63666.667 | D23: =B21+B22 -> -63666.667 | E23: =B21+B22 -> -63666.667 | F23: =B21+B22 -> -63666.667 | G23: =B21+B22 -> -63666.667 | H23: =B21+B22 -> -63666.667 | I23: =B21+B22 -> -63666.667 | J23: =B21+B22 -> -63666.667 | K23: =B21+B22 -> -63666.667 | L23: =B21+B22 -> -63666.667 | M23: =B21+B22 -> -63666.667 | N23: =SUM(B23:M23) -> -764000
A24: Taux de marge nette | B24: =IF(B8<>0,B23/B8,0) -> -0.34107143 | C24: =IF(B8<>0,B23/B8,0) -> -0.34107143 | D24: =IF(B8<>0,B23/B8,0) -> -0.34107143 | E24: =IF(B8<>0,B23/B8,0) -> -0.34107143 | F24: =IF(B8<>0,B23/B8,0) -> -0.34107143 | G24: =IF(B8<>0,B23/B8,0) -> -0.34107143 | H24: =IF(B8<>0,B23/B8,0) -> -0.34107143 | I24: =IF(B8<>0,B23/B8,0) -> -0.34107143 | J24: =IF(B8<>0,B23/B8,0) -> -0.34107143 | K24: =IF(B8<>0,B23/B8,0) -> -0.34107143 | L24: =IF(B8<>0,B23/B8,0) -> -0.34107143 | M24: =IF(B8<>0,B23/B8,0) -> -0.34107143 | N24: =IF(N8<>0,N23/N8,0) -> -0.34107143

Sheet Trésorerie
A2: PRÉVISIONNEL DE TRÉSORERIE 2026 — MENSUEL
A5: RUBRIQUE | B5: Jan | C5: Fév | D5: Mar | E5: Avr | F5: Mai | G5: Jun | H5: Jul | I5: Aoû | J5: Sep | K5: Oct | L5: Nov | M5: Déc | N5: TOTAL
A6: SOLDE DE TRÉSORERIE
A7: Solde trésorerie en début de mois | B7: =Hypothèses!$B$26 -> 30
A8: ENCAISSEMENTS
A9: Encaissements clients (CA HT) | B9: ='Budget P&L'!B8 -> 186666.67 | C9: ='Budget P&L'!C8 -> 186666.67 | D9: ='Budget P&L'!D8 -> 186666.67 | E9: ='Budget P&L'!E8 -> 186666.67 | F9: ='Budget P&L'!F8 -> 186666.67 | G9: ='Budget P&L'!G8 -> 186666.67 | H9: ='Budget P&L'!H8 -> 186666.67 | I9: ='Budget P&L'!I8 -> 186666.67 | ... M9: ='Budget P&L'!M8 -> 186666.67 | N9: =SUM(B9:M9) -> 2240000
A10: Autres encaissements (subventions, cessions…) | B10: 0 | C10: 0 | D10: 0 | E10: 0 | F10: 0 | G10: 0 | H10: 0 | I10: 0 | J10: 0 | K10: 0 | L10: 0 | M10: 0 | N10: =SUM(B10:M10) -> 0
A11: ▶ TOTAL ENCAISSEMENTS | B11: =B9+B10 -> 186666.67 | C11: =B9+B10 -> 186666.67 | D11: =B9+B10 -> 186666.67 | E11: =B9+B10 -> 186666.67 | F11: =B9+B10 -> 186666.67 | G11: =B9+B10 -> 186666.67 | H11: =B9+B10 -> 186666.67 | I11: =B9+B10 -> 186666.67 | J11: =B9+B10 -> 186666.67 | K11: =B9+B10 -> 186666.67 | L11: =B9+B10 -> 186666.67 | M11: =B9+B10 -> 186666.67 | N11: =SUM(B11:M11) -> 2240000
A12: DÉCAISSEMENTS
A13: (-) Charges de personnel | B13: =Hypothèses!$B$30/12 -> 0 | C13: =Hypothèses!$B$30/12 -> 0 | D13: =Hypothèses!$B$30/12 -> 0 | E13: =Hypothèses!$B$30/12 -> 0 | F13: =Hypothèses!$B$30/12 -> 0 | G13: =Hypothèses!$B$30/12 -> 0 | H13: =Hypothèses!$B$30/12 -> 0 | I13: =Hypothèses!$B$30/12 -> 0 | ... M13: =Hypothèses!$B$30/12 -> 0 | N13: =SUM(B13:M13) -> 0
A14: (-) Loyer & charges locatives | B14: =Hypothèses!$B$31/12 -> 40000 | C14: =Hypothèses!$B$31/12 -> 40000 | D14: =Hypothèses!$B$31/12 -> 40000 | E14: =Hypothèses!$B$31/12 -> 40000 | F14: =Hypothèses!$B$31/12 -> 40000 | G14: =Hypothèses!$B$31/12 -> 40000 | H14: =Hypothèses!$B$31/12 -> 40000 | I14: =Hypothèses!$B$31/12 -> 40000 | ... M14: =Hypothèses!$B$31/12 -> 40000 | N14: =SUM(B14:M14) -> 480000
A15: (-) Paiement fournisseurs | B15: ='Budget P&L'!B10*-1 -> 186666.67 | C15: ='Budget P&L'!C10*-1 -> 186666.67 | D15: ='Budget P&L'!D10*-1 -> 186666.67 | E15: ='Budget P&L'!E10*-1 -> 186666.67 | F15: ='Budget P&L'!F10*-1 -> 186666.67 | G15: ='Budget P&L'!G10*-1 -> 186666.67 | H15: ='Budget P&L'!H10*-1 -> 186666.67 | I15: ='Budget P&L'!I10*-1 -> 186666.67 | ... M15: ='Budget P&L'!M10*-1 -> 186666.67 | N15: =SUM(B15:M15) -> 2240000
A16: (-) Acomptes IS (trimestriels) | B16: 0 | C16: 0 | D16: ='Budget P&L'!N22*-1/4 -> 0 | E16: 0 | F16: 0 | G16: ='Budget P&L'!N22*-1/4 -> 0 | H16: 0 | I16: 0 | J16: ='Budget P&L'!N22*-1/4 -> 0 | K16: 0 | L16: 0 | M16: ='Budget P&L'!N22*-1/4 -> 0 | N16: =SUM(B16:M16) -> 0
A17: (-) Autres charges fixes décaissées | B17: =Hypothèses!$B$33/12 -> 2000 | C17: =Hypothèses!$B$33/12 -> 2000 | D17: =Hypothèses!$B$33/12 -> 2000 | E17: =Hypothèses!$B$33/12 -> 2000 | F17: =Hypothèses!$B$33/12 -> 2000 | G17: =Hypothèses!$B$33/12 -> 2000 | H17: =Hypothèses!$B$33/12 -> 2000 | I17: =Hypothèses!$B$33/12 -> 2000 | ... M17: =Hypothèses!$B$33/12 -> 2000 | N17: =SUM(B17:M17) -> 24000
A18: (-) Investissements / CAPEX | B18: 0 | C18: 0 | D18: 0 | E18: 0 | F18: 0 | G18: 0 | H18: 0 | I18: 0 | J18: 0 | K18: 0 | L18: 0 | M18: 0 | N18: =SUM(B18:M18) -> 0
A19: ▶ TOTAL DÉCAISSEMENTS | B19: =B13+B14+B15+B16+B17+B18 -> 228666.67 | C19: =B13+B14+B15+B16+B17+B18 -> 228666.67 | D19: =B13+B14+B15+B16+B17+B18 -> 228666.67 | E19: =B13+B14+B15+B16+B17+B18 -> 228666.67 | F19: =B13+B14+B15+B16+B17+B18 -> 228666.67 | G19: =B13+B14+B15+B16+B17+B18 -> 228666.67 | H19: =B13+B14+B15+B16+B17+B18 -> 228666.67 | I19: =B13+B14+B15+B16+B17+B18 -> 228666.67 | J19: =B13+B14+B15+B16+B17+B18 -> 228666.67 | K19: =B13+B14+B15+B16+B17+B18 -> 228666.67 | L19: =B13+B14+B15+B16+B17+B18 -> 228666.67 | M19: =B13+B14+B15+B16+B17+B18 -> 228666.67 | N19: =SUM(B19:M19) -> 2744000
A20: ▶ FLUX NET DU MOIS | B20: =B11-B19 -> -42000 | C20: =B11-B19 -> -42000 | D20: =B11-B19 -> -42000 | E20: =B11-B19 -> -42000 | F20: =B11-B19 -> -42000 | G20: =B11-B19 -> -42000 | H20: =B11-B19 -> -42000 | I20: =B11-B19 -> -42000 | J20: =B11-B19 -> -42000 | K20: =B11-B19 -> -42000 | L20: =B11-B19 -> -42000 | M20: =B11-B19 -> -42000 | N20: =SUM(B20:M20) -> -504000
A21: ▶ SOLDE EN FIN DE MOIS | B21: =Hypothèses!$B$26+B20 -> -41970 | C21: =B21+C20 -> -83970 | D21: =C21+D20 -> -125970 | E21: =D21+E20 -> -167970 | F21: =E21+F20 -> -209970 | G21: =F21+G20 -> -251970 | H21: =G21+H20 -> -293970 | I21: =H21+I20 -> -335970 | J21: =I21+J20 -> -377970 | ... M21: =L21+M20 -> -503970 | N21: =M21 -> -503970
A22: Alerte seuil de sécurité | B22: =IF(B21<Hypothèses!$B$27,"⚠️ SOUS SEUIL","✅ OK") -> ⚠️ SOUS SEUIL | C22: =IF(C21<Hypothèses!$B$27,"⚠️ SOUS SEUIL","✅ OK") -> ⚠️ SOUS SEUIL | D22: =IF(D21<Hypothèses!$B$27,"⚠️ SOUS SEUIL","✅ OK") -> ⚠️ SOUS SEUIL | E22: =IF(E21<Hypothèses!$B$27,"⚠️ SOUS SEUIL","✅ OK") -> ⚠️ SOUS SEUIL | F22: =IF(F21<Hypothèses!$B$27,"⚠️ SOUS SEUIL","✅ OK") -> ⚠️ SOUS SEUIL | G22: =IF(G21<Hypothèses!$B$27,"⚠️ SOUS SEUIL","✅ OK") -> ⚠️ SOUS SEUIL | H22: =IF(H21<Hypothèses!$B$27,"⚠️ SOUS SEUIL","✅ OK") -> ⚠️ SOUS SEUIL | I22: =IF(I21<Hypothèses!$B$27,"⚠️ SOUS SEUIL","✅ OK") -> ⚠️ SOUS SEUIL | ... M22: =IF(M21<Hypothèses!$B$27,"⚠️ SOUS SEUIL","✅ OK") -> ⚠️ SOUS SEUIL
