Workbook

Sheet Dashboard
A2: DASHBOARD CASH FLOW 2026 — VUE SYNTHÈSE
A5: KPIs TRÉSORERIE — ANNÉE 2026
A6: TOTAL ENCAISSEMENTS | C6: FLUX NET ANNUEL | E6: SOLDE FIN DÉCEMBRE
A7: ='Flux Mensuels'!N11 -> 0 | C7: ='Flux Mensuels'!N24 -> 0 | E7: ='Flux Mensuels'!M25 -> 80000
A8: Cumulé 12 mois | C8: Encaiss. − Décaiss. | E8: Tréso de clôture
A11: SOLDE OUVERTURE | C11: SEUIL ALERTE | E11: MOIS SOUS SEUIL
A12: =Config!$B$11 -> 80000 | C12: =Config!$B$12 -> 20000 | E12: =COUNTIF('Flux Mensuels'!B26:M26,"🚨 ALERTE") -> 0
A13: Au 01/01/2026 | C13: Seuil de vigilance | E13: Nombre de mois critiques
A17: SYNTHÈSE MENSUELLE
A18: Mois | B18: Encaissements | C18: Décaissements | D18: Flux net | E18: Solde fin mois | F18: Statut
A19: Jan | B19: ='Flux Mensuels'!B11 -> 0 | C19: ='Flux Mensuels'!B18+'Flux Mensuels'!B22 -> 0 | D19: ='Flux Mensuels'!B24 -> 0 | E19: ='Flux Mensuels'!B25 -> 80000 | F19: ='Flux Mensuels'!B26 -> ✅ OK
A20: Fév | B20: ='Flux Mensuels'!C11 -> 0 | C20: ='Flux Mensuels'!C18+'Flux Mensuels'!C22 -> 0 | D20: ='Flux Mensuels'!C24 -> 0 | E20: ='Flux Mensuels'!C25 -> 80000 | F20: ='Flux Mensuels'!C26 -> ✅ OK
A21: Mar | B21: ='Flux Mensuels'!D11 -> 0 | C21: ='Flux Mensuels'!D18+'Flux Mensuels'!D22 -> 0 | D21: ='Flux Mensuels'!D24 -> 0 | E21: ='Flux Mensuels'!D25 -> 80000 | F21: ='Flux Mensuels'!D26 -> ✅ OK
A22: Avr | B22: ='Flux Mensuels'!E11 -> 0 | C22: ='Flux Mensuels'!E18+'Flux Mensuels'!E22 -> 0 | D22: ='Flux Mensuels'!E24 -> 0 | E22: ='Flux Mensuels'!E25 -> 80000 | F22: ='Flux Mensuels'!E26 -> ✅ OK
A23: Mai | B23: ='Flux Mensuels'!F11 -> 0 | C23: ='Flux Mensuels'!F18+'Flux Mensuels'!F22 -> 0 | D23: ='Flux Mensuels'!F24 -> 0 | E23: ='Flux Mensuels'!F25 -> 80000 | F23: ='Flux Mensuels'!F26 -> ✅ OK
A24: Jun | B24: ='Flux Mensuels'!G11 -> 0 | C24: ='Flux Mensuels'!G18+'Flux Mensuels'!G22 -> 0 | D24: ='Flux Mensuels'!G24 -> 0 | E24: ='Flux Mensuels'!G25 -> 80000 | F24: ='Flux Mensuels'!G26 -> ✅ OK
A25: Jul | B25: ='Flux Mensuels'!H11 -> 0 | C25: ='Flux Mensuels'!H18+'Flux Mensuels'!H22 -> 0 | D25: ='Flux Mensuels'!H24 -> 0 | E25: ='Flux Mensuels'!H25 -> 80000 | F25: ='Flux Mensuels'!H26 -> ✅ OK
A26: Aoû | B26: ='Flux Mensuels'!I11 -> 0 | C26: ='Flux Mensuels'!I18+'Flux Mensuels'!I22 -> 0 | D26: ='Flux Mensuels'!I24 -> 0 | E26: ='Flux Mensuels'!I25 -> 80000 | F26: ='Flux Mensuels'!I26 -> ✅ OK
A27: Sep | B27: ='Flux Mensuels'!J11 -> 0 | C27: ='Flux Mensuels'!J18+'Flux Mensuels'!J22 -> 0 | D27: ='Flux Mensuels'!J24 -> 0 | E27: ='Flux Mensuels'!J25 -> 80000 | F27: ='Flux Mensuels'!J26 -> ✅ OK
A28: Oct | B28: ='Flux Mensuels'!K11 -> 0 | C28: ='Flux Mensuels'!K18+'Flux Mensuels'!K22 -> 0 | D28: ='Flux Mensuels'!K24 -> 0 | E28: ='Flux Mensuels'!K25 -> 80000 | F28: ='Flux Mensuels'!K26 -> ✅ OK
A29: Nov | B29: ='Flux Mensuels'!L11 -> 0 | C29: ='Flux Mensuels'!L18+'Flux Mensuels'!L22 -> 0 | D29: ='Flux Mensuels'!L24 -> 0 | E29: ='Flux Mensuels'!L25 -> 80000 | F29: ='Flux Mensuels'!L26 -> ✅ OK
A30: Déc | B30: ='Flux Mensuels'!M11 -> 0 | C30: ='Flux Mensuels'!M18+'Flux Mensuels'!M22 -> 0 | D30: ='Flux Mensuels'!M24 -> 0 | E30: ='Flux Mensuels'!M25 -> 80000 | F30: ='Flux Mensuels'!M26 -> ✅ OK

Sheet Config
A2: DASHBOARD CASH FLOW 2026 — CONFIGURATION
A4: FinSight · Pilotage financier PME · finsight.zineinsight.com
A6: 🏢 INFORMATIONS ENTREPRISE
A7: Nom de l'entreprise | B7: Ma PME SAS | C7: Votre raison sociale
A8: Secteur d'activité | B8: Services | C8: Services / Commerce / Industrie
A10: 🏦 PARAMÈTRES TRÉSORERIE
A11: Solde trésorerie 01/01/2026 | B11: 80000 | C11: Solde d'ouverture réel
A12: Seuil alerte trésorerie basse | B12: 20000 | C12: Alerte si solde < ce montant
A13: Seuil trésorerie confort | B13: 50000 | C13: Zone de confort
A15: 📊 PARAMÈTRES D'ANALYSE
A16: DSO moyen (jours) | B16: 45 | C16: Délai encaissement clients
A17: DPO moyen (jours) | B17: 30 | C17: Délai paiement fournisseurs
A18: Taux TVA collectée | B18: 0.2 | C18: TVA sur ventes
A21: ⚡ Cellules jaunes = INPUTS à modifier. 📊 Saisissez vos flux dans 'Flux Mensuels'. 🎯 Dashboard et Projection se calculent automatiquement.

Sheet Flux Mensuels
A2: CASH FLOW — ENCAISSEMENTS & DÉCAISSEMENTS MENSUELS
A5: RUBRIQUE | B5: Jan | C5: Fév | D5: Mar | E5: Avr | F5: Mai | G5: Jun | H5: Jul | I5: Aoû | J5: Sep | K5: Oct | L5: Nov | M5: Déc | N5: TOTAL
A6: → Colonnes jaunes = saisie mensuelle. Les totaux et indicateurs sont calculés automatiquement.
A7: ENCAISSEMENTS
A8: Encaissements clients (CA HT) | B8: 0 | C8: 0 | D8: 0 | E8: 0 | F8: 0 | G8: 0 | H8: 0 | I8: 0 | J8: 0 | K8: 0 | L8: 0 | M8: 0 | N8: =SUM(B8:M8) -> 0
A9: Avances & acomptes reçus | B9: 0 | C9: 0 | D9: 0 | E9: 0 | F9: 0 | G9: 0 | H9: 0 | I9: 0 | J9: 0 | K9: 0 | L9: 0 | M9: 0 | N9: =SUM(B9:M9) -> 0
A10: Autres encaissements (subventions, cessions…) | B10: 0 | C10: 0 | D10: 0 | E10: 0 | F10: 0 | G10: 0 | H10: 0 | I10: 0 | J10: 0 | K10: 0 | L10: 0 | M10: 0 | N10: =SUM(B10:M10) -> 0
A11: ▶ TOTAL ENCAISSEMENTS | B11: =B8+B9+B10 -> 0 | C11: =C8+C9+C10 -> 0 | D11: =D8+D9+D10 -> 0 | E11: =E8+E9+E10 -> 0 | F11: =F8+F9+F10 -> 0 | G11: =G8+G9+G10 -> 0 | H11: =H8+H9+H10 -> 0 | I11: =I8+I9+I10 -> 0 | ... M11: =M8+M9+M10 -> 0 | N11: =SUM(B11:M11) -> 0
A12: DÉCAISSEMENTS — EXPLOITATION
A13: (-) Charges de personnel | B13: 0 | C13: 0 | D13: 0 | E13: 0 | F13: 0 | G13: 0 | H13: 0 | I13: 0 | J13: 0 | K13: 0 | L13: 0 | M13: 0 | N13: =SUM(B13:M13) -> 0
A14: (-) Loyer & charges locatives | B14: 0 | C14: 0 | D14: 0 | E14: 0 | F14: 0 | G14: 0 | H14: 0 | I14: 0 | J14: 0 | K14: 0 | L14: 0 | M14: 0 | N14: =SUM(B14:M14) -> 0
A15: (-) Paiements fournisseurs | B15: 0 | C15: 0 | D15: 0 | E15: 0 | F15: 0 | G15: 0 | H15: 0 | I15: 0 | J15: 0 | K15: 0 | L15: 0 | M15: 0 | N15: =SUM(B15:M15) -> 0
A16: (-) Impôts & taxes (IS, TVA nette…) | B16: 0 | C16: 0 | D16: 0 | E16: 0 | F16: 0 | G16: 0 | H16: 0 | I16: 0 | J16: 0 | K16: 0 | L16: 0 | M16: 0 | N16: =SUM(B16:M16) -> 0
A17: (-) Autres charges exploitation | B17: 0 | C17: 0 | D17: 0 | E17: 0 | F17: 0 | G17: 0 | H17: 0 | I17: 0 | J17: 0 | K17: 0 | L17: 0 | M17: 0 | N17: =SUM(B17:M17) -> 0
A18: ▶ TOTAL DÉCAISSEMENTS EXPLOITATION | B18: =B13+B14+B15+B16+B17 -> 0 | C18: =C13+C14+C15+C16+C17 -> 0 | D18: =D13+D14+D15+D16+D17 -> 0 | E18: =E13+E14+E15+E16+E17 -> 0 | F18: =F13+F14+F15+F16+F17 -> 0 | G18: =G13+G14+G15+G16+G17 -> 0 | H18: =H13+H14+H15+H16+H17 -> 0 | I18: =I13+I14+I15+I16+I17 -> 0 | ... M18: =M13+M14+M15+M16+M17 -> 0 | N18: =SUM(B18:M18) -> 0
A19: DÉCAISSEMENTS — INVESTISSEMENT
A20: (-) Investissements / CAPEX | B20: 0 | C20: 0 | D20: 0 | E20: 0 | F20: 0 | G20: 0 | H20: 0 | I20: 0 | J20: 0 | K20: 0 | L20: 0 | M20: 0 | N20: =SUM(B20:M20) -> 0
A21: (-) Remboursements d'emprunts | B21: 0 | C21: 0 | D21: 0 | E21: 0 | F21: 0 | G21: 0 | H21: 0 | I21: 0 | J21: 0 | K21: 0 | L21: 0 | M21: 0 | N21: =SUM(B21:M21) -> 0
A22: ▶ TOTAL DÉCAISSEMENTS INVESTISSEMENT | B22: =B20+B21 -> 0 | C22: =C20+C21 -> 0 | D22: =D20+D21 -> 0 | E22: =E20+E21 -> 0 | F22: =F20+F21 -> 0 | G22: =G20+G21 -> 0 | H22: =H20+H21 -> 0 | I22: =I20+I21 -> 0 | ... M22: =M20+M21 -> 0 | N22: =SUM(B22:M22) -> 0
A23: SYNTHÈSE TRÉSORERIE
A24: ▶ FLUX NET DU MOIS | B24: =B11-B18-B22 -> 0 | C24: =C11-C18-C22 -> 0 | D24: =D11-D18-D22 -> 0 | E24: =E11-E18-E22 -> 0 | F24: =F11-F18-F22 -> 0 | G24: =G11-G18-G22 -> 0 | H24: =H11-H18-H22 -> 0 | I24: =I11-I18-I22 -> 0 | ... M24: =M11-M18-M22 -> 0 | N24: =SUM(B24:M24) -> 0
A25: ▶ SOLDE EN FIN DE MOIS | B25: =Config!$B$11+B24 -> 80000 | C25: =B25+C24 -> 80000 | D25: =C25+D24 -> 80000 | E25: =D25+E24 -> 80000 | F25: =E25+F24 -> 80000 | G25: =F25+G24 -> 80000 | H25: =G25+H24 -> 80000 | I25: =H25+I24 -> 80000 | J25: =I25+J24 -> 80000 | ... M25: =L25+M24 -> 80000 | N25: =M25 -> 80000
A26: Alerte seuil de sécurité | B26: =IF(B25<Config!$B$12,"🚨 ALERTE",IF(B25<Config!$B$13,"⚠️ Surveiller","✅ OK")) -> ✅ OK | C26: =IF(C25<Config!$B$12,"🚨 ALERTE",IF(C25<Config!$B$13,"⚠️ Surveiller","✅ OK")) -> ✅ OK | D26: =IF(D25<Config!$B$12,"🚨 ALERTE",IF(D25<Config!$B$13,"⚠️ Surveiller","✅ OK")) -> ✅ OK | E26: =IF(E25<Config!$B$12,"🚨 ALERTE",IF(E25<Config!$B$13,"⚠️ Surveiller","✅ OK")) -> ✅ OK | F26: =IF(F25<Config!$B$12,"🚨 ALERTE",IF(F25<Config!$B$13,"⚠️ Surveiller","✅ OK")) -> ✅ OK | G26: =IF(G25<Config!$B$12,"🚨 ALERTE",IF(G25<Config!$B$13,"⚠️ Surveiller","✅ OK")) -> ✅ OK | H26: =IF(H25<Config!$B$12,"🚨 ALERTE",IF(H25<Config!$B$13,"⚠️ Surveiller","✅ OK")) -> ✅ OK | I26: =IF(I25<Config!$B$12,"🚨 ALERTE",IF(I25<Config!$B$13,"⚠️ Surveiller","✅ OK")) -> ✅ OK | ... M26: =IF(M25<Config!$B$12,"🚨 ALERTE",IF(M25<Config!$B$13,"⚠️ Surveiller","✅ OK")) -> ✅ OK

Sheet Projection 6 Mois
A2: PROJECTION TRÉSORERIE — 6 MOIS GLISSANTS
A5: SCÉNARIO | B5: M+1 | C5: M+2 | D5: M+3 | E5: M+4 | F5: M+5 | G5: M+6 | H5: Fin M+6
A6: → Saisissez vos hypothèses de flux prévisionnels pour les 6 prochains mois.
A7: SCÉNARIO BASE (hypothèses prévisionnelles)
A8: Encaissements prévisionnels | B8: 0 | C8: 0 | D8: 0 | E8: 0 | F8: 0 | G8: 0 | H8: =SUM(B8:G8) -> 0
A9: Décaissements prévisionnels | B9: 0 | C9: 0 | D9: 0 | E9: 0 | F9: 0 | G9: 0 | H9: =SUM(B9:G9) -> 0
A10: Flux net mensuel | B10: =B8-B9 -> 0 | C10: =C8-C9 -> 0 | D10: =D8-D9 -> 0 | E10: =E8-E9 -> 0 | F10: =F8-F9 -> 0 | G10: =G8-G9 -> 0 | H10: =SUM(B10:G10) -> 0
A11: Solde prévisionnel fin de mois | B11: =Config!$B$11+B10 -> 80000 | C11: =B11+C10 -> 80000 | D11: =C11+D10 -> 80000 | E11: =D11+E10 -> 80000 | F11: =E11+F10 -> 80000 | G11: =F11+G10 -> 80000 | H11: =G11 -> 80000
A12: Alerte seuil | B12: =IF(B11<Config!$B$12,"🚨 ALERTE",IF(B11<Config!$B$13,"⚠️ Surveiller","✅ OK")) -> ✅ OK | C12: =IF(C11<Config!$B$12,"🚨 ALERTE",IF(C11<Config!$B$13,"⚠️ Surveiller","✅ OK")) -> ✅ OK | D12: =IF(D11<Config!$B$12,"🚨 ALERTE",IF(D11<Config!$B$13,"⚠️ Surveiller","✅ OK")) -> ✅ OK | E12: =IF(E11<Config!$B$12,"🚨 ALERTE",IF(E11<Config!$B$13,"⚠️ Surveiller","✅ OK")) -> ✅ OK | F12: =IF(F11<Config!$B$12,"🚨 ALERTE",IF(F11<Config!$B$13,"⚠️ Surveiller","✅ OK")) -> ✅ OK | G12: =IF(G11<Config!$B$12,"🚨 ALERTE",IF(G11<Config!$B$13,"⚠️ Surveiller","✅ OK")) -> ✅ OK
A14: SCÉNARIO PESSIMISTE (−20 % encaissements)
A15: Encaissements (×0.8) | B15: =B8*0.8 -> 0 | C15: =C8*0.8 -> 0 | D15: =D8*0.8 -> 0 | E15: =E8*0.8 -> 0 | F15: =F8*0.8 -> 0 | G15: =G8*0.8 -> 0 | H15: =SUM(B15:G15) -> 0
A16: Solde pessimiste fin de mois | B16: =Config!$B$11+(B15-B9) -> 80000 | C16: =B16+(C15-C9) -> 80000 | D16: =C16+(D15-D9) -> 80000 | E16: =D16+(E15-E9) -> 80000 | F16: =E16+(F15-F9) -> 80000 | G16: =F16+(G15-G9) -> 80000 | H16: =G16 -> 80000
A18: SCÉNARIO OPTIMISTE (+15 % encaissements)
A19: Encaissements (×1.15) | B19: =B8*1.15 -> 0 | C19: =C8*1.15 -> 0 | D19: =D8*1.15 -> 0 | E19: =E8*1.15 -> 0 | F19: =F8*1.15 -> 0 | G19: =G8*1.15 -> 0 | H19: =SUM(B19:G19) -> 0
A20: Solde optimiste fin de mois | B20: =Config!$B$11+(B19-B9) -> 80000 | C20: =B20+(C19-C9) -> 80000 | D20: =C20+(D19-D9) -> 80000 | E20: =D20+(E19-E9) -> 80000 | F20: =E20+(F19-F9) -> 80000 | G20: =F20+(G19-G9) -> 80000 | H20: =G20 -> 80000
A22: 📌 MODE D'EMPLOI 1. Saisissez vos encaissements et décaissements prévisionnels mois par mois. 2. Les scénarios pessimiste (−20 %) et optimiste (+15 %) se calculent automatiquement. 3. L'alerte passe en 🚨 si le solde prévisionnel passe sous le seuil configuré. 💡 FinSight — finsight.zineinsight.com
