Workbook

Sheet Saisie mensuelle
A1: TABLEAU DE BORD EBITDA MENSUEL — FinSight
A2: Saisissez vos données en bleu · Les formules calculent automatiquement
A4: INDICATEURS | B4: Jan | C4: Fév | D4: Mar | E4: Avr | F4: Mai | G4: Jui | H4: Jul | I4: Aoû | J4: Sep | K4: Oct | L4: Nov | M4: Déc | N4: TOTAL
A5: ▶ CHIFFRE D'AFFAIRES
A6: Chiffre d'affaires (€) | B6: 0 | C6: 0 | D6: 0 | E6: 0 | F6: 0 | G6: 0 | H6: 0 | I6: 0 | J6: 0 | K6: 0 | L6: 0 | M6: 0 | N6: =SUM(B6:M6) -> 0
A8: ▶ CHARGES OPÉRATIONNELLES [saisir en positif]
A9: Achats & charges externes (€) | B9: 0 | C9: 0 | D9: 0 | E9: 0 | F9: 0 | G9: 0 | H9: 0 | I9: 0 | J9: 0 | K9: 0 | L9: 0 | M9: 0 | N9: =SUM(B9:M9) -> 0
A10: Masse salariale brute (€) | B10: 0 | C10: 0 | D10: 0 | E10: 0 | F10: 0 | G10: 0 | H10: 0 | I10: 0 | J10: 0 | K10: 0 | L10: 0 | M10: 0 | N10: =SUM(B10:M10) -> 0
A11: Charges sociales patronales (€) | B11: 0 | C11: 0 | D11: 0 | E11: 0 | F11: 0 | G11: 0 | H11: 0 | I11: 0 | J11: 0 | K11: 0 | L11: 0 | M11: 0 | N11: =SUM(B11:M11) -> 0
A12: Autres charges opérationnelles (€) | B12: 0 | C12: 0 | D12: 0 | E12: 0 | F12: 0 | G12: 0 | H12: 0 | I12: 0 | J12: 0 | K12: 0 | L12: 0 | M12: 0 | N12: =SUM(B12:M12) -> 0
A14: ▶ CALCUL EBITDA
A15: Total charges opérationnelles (€) | B15: =B9+B10+B11+B12 -> 0 | C15: =C9+C10+C11+C12 -> 0 | D15: =D9+D10+D11+D12 -> 0 | E15: =E9+E10+E11+E12 -> 0 | F15: =F9+F10+F11+F12 -> 0 | G15: =G9+G10+G11+G12 -> 0 | H15: =H9+H10+H11+H12 -> 0 | I15: =I9+I10+I11+I12 -> 0 | ... M15: =M9+M10+M11+M12 -> 0 | N15: =SUM(B15:M15) -> 0
A16: EBITDA (€) | B16: =B6-B15 -> 0 | C16: =C6-C15 -> 0 | D16: =D6-D15 -> 0 | E16: =E6-E15 -> 0 | F16: =F6-F15 -> 0 | G16: =G6-G15 -> 0 | H16: =H6-H15 -> 0 | I16: =I6-I15 -> 0 | ... M16: =M6-M15 -> 0 | N16: =SUM(B16:M16) -> 0
A17: Marge EBITDA (%) | B17: =IF(B6=0,0,B16/B6) -> 0 | C17: =IF(C6=0,0,C16/C6) -> 0 | D17: =IF(D6=0,0,D16/D6) -> 0 | E17: =IF(E6=0,0,E16/E6) -> 0 | F17: =IF(F6=0,0,F16/F6) -> 0 | G17: =IF(G6=0,0,G16/G6) -> 0 | H17: =IF(H6=0,0,H16/H6) -> 0 | I17: =IF(I6=0,0,I16/I6) -> 0 | ... N17: =IF(N6=0,0,N16/N6) -> 0
A20: ▶ ALERTES AUTOMATIQUES
A21: Benchmark sectoriel cible (%) | B21: 0.1
A22: Statut marge EBITDA | B22: =IF(B6=0,"—",IF(B17>=$B$21,"✓ OK","⚠ Sous seuil")) -> — | C22: =IF(C6=0,"—",IF(C17>=$B$21,"✓ OK","⚠ Sous seuil")) -> — | D22: =IF(D6=0,"—",IF(D17>=$B$21,"✓ OK","⚠ Sous seuil")) -> — | E22: =IF(E6=0,"—",IF(E17>=$B$21,"✓ OK","⚠ Sous seuil")) -> — | F22: =IF(F6=0,"—",IF(F17>=$B$21,"✓ OK","⚠ Sous seuil")) -> — | G22: =IF(G6=0,"—",IF(G17>=$B$21,"✓ OK","⚠ Sous seuil")) -> — | H22: =IF(H6=0,"—",IF(H17>=$B$21,"✓ OK","⚠ Sous seuil")) -> — | I22: =IF(I6=0,"—",IF(I17>=$B$21,"✓ OK","⚠ Sous seuil")) -> — | ... M22: =IF(M6=0,"—",IF(M17>=$B$21,"✓ OK","⚠ Sous seuil")) -> —
A25: 💡 Formule canonique FinSight : EBITDA = Résultat net + Impôts + Intérêts + Amortissements | Ici : EBITDA = CA - Charges opérationnelles (approche top-down PME)

Sheet Dashboard
A1: DASHBOARD EBITDA — VUE SYNTHÉTIQUE
A2: Données tirées de l'onglet Saisie mensuelle · Mise à jour automatique
B5: CA ANNUEL (€) | E5: EBITDA ANNUEL (€) | H5: MARGE EBITDA | K5: BENCHMARK CIBLE
B6: ='Saisie mensuelle'!N6 -> 0 | E6: ='Saisie mensuelle'!N16 -> 0 | H6: =IF('Saisie mensuelle'!N6=0,0,'Saisie mensuelle'!N16/'Saisie mensuelle'!N6) -> 0 | K6: ='Saisie mensuelle'!B21 -> 0.1
H7: =IF('Saisie mensuelle'!N6=0,"—",IF('Saisie mensuelle'!N16/'Saisie mensuelle'!N6>='Saisie mensuelle'!B21,"✓ Objectif atteint","⚠ Sous objectif")) -> —
A11: ▶ RÉCAPITULATIF MENSUEL
A12: MOIS | B12: CA (€) | D12: Charges op. (€) | F12: EBITDA (€) | H12: Marge EBITDA (%)
A13: Jan | B13: ='Saisie mensuelle'!B6 -> 0 | D13: ='Saisie mensuelle'!B15 -> 0 | F13: ='Saisie mensuelle'!B16 -> 0 | H13: ='Saisie mensuelle'!B17 -> 0
A14: Fév | B14: ='Saisie mensuelle'!C6 -> 0 | D14: ='Saisie mensuelle'!C15 -> 0 | F14: ='Saisie mensuelle'!C16 -> 0 | H14: ='Saisie mensuelle'!C17 -> 0
A15: Mar | B15: ='Saisie mensuelle'!D6 -> 0 | D15: ='Saisie mensuelle'!D15 -> 0 | F15: ='Saisie mensuelle'!D16 -> 0 | H15: ='Saisie mensuelle'!D17 -> 0
A16: Avr | B16: ='Saisie mensuelle'!E6 -> 0 | D16: ='Saisie mensuelle'!E15 -> 0 | F16: ='Saisie mensuelle'!E16 -> 0 | H16: ='Saisie mensuelle'!E17 -> 0
A17: Mai | B17: ='Saisie mensuelle'!F6 -> 0 | D17: ='Saisie mensuelle'!F15 -> 0 | F17: ='Saisie mensuelle'!F16 -> 0 | H17: ='Saisie mensuelle'!F17 -> 0
A18: Jui | B18: ='Saisie mensuelle'!G6 -> 0 | D18: ='Saisie mensuelle'!G15 -> 0 | F18: ='Saisie mensuelle'!G16 -> 0 | H18: ='Saisie mensuelle'!G17 -> 0
A19: Jul | B19: ='Saisie mensuelle'!H6 -> 0 | D19: ='Saisie mensuelle'!H15 -> 0 | F19: ='Saisie mensuelle'!H16 -> 0 | H19: ='Saisie mensuelle'!H17 -> 0
A20: Aoû | B20: ='Saisie mensuelle'!I6 -> 0 | D20: ='Saisie mensuelle'!I15 -> 0 | F20: ='Saisie mensuelle'!I16 -> 0 | H20: ='Saisie mensuelle'!I17 -> 0
A21: Sep | B21: ='Saisie mensuelle'!J6 -> 0 | D21: ='Saisie mensuelle'!J15 -> 0 | F21: ='Saisie mensuelle'!J16 -> 0 | H21: ='Saisie mensuelle'!J17 -> 0
A22: Oct | B22: ='Saisie mensuelle'!K6 -> 0 | D22: ='Saisie mensuelle'!K15 -> 0 | F22: ='Saisie mensuelle'!K16 -> 0 | H22: ='Saisie mensuelle'!K17 -> 0
A23: Nov | B23: ='Saisie mensuelle'!L6 -> 0 | D23: ='Saisie mensuelle'!L15 -> 0 | F23: ='Saisie mensuelle'!L16 -> 0 | H23: ='Saisie mensuelle'!L17 -> 0
A24: Déc | B24: ='Saisie mensuelle'!M6 -> 0 | D24: ='Saisie mensuelle'!M15 -> 0 | F24: ='Saisie mensuelle'!M16 -> 0 | H24: ='Saisie mensuelle'!M17 -> 0
A25: TOTAL / MOY | B25: ='Saisie mensuelle'!N6 -> 0 | D25: ='Saisie mensuelle'!N15 -> 0 | F25: ='Saisie mensuelle'!N16 -> 0 | H25: =IF('Saisie mensuelle'!N6=0,0,'Saisie mensuelle'!N16/'Saisie mensuelle'!N6) -> 0
A28: Mois | B28: EBITDA (€) | C28: Marge (%)
A29: Jan | B29: ='Saisie mensuelle'!B16 -> 0 | C29: ='Saisie mensuelle'!B17 -> 0
A30: Fév | B30: ='Saisie mensuelle'!C16 -> 0 | C30: ='Saisie mensuelle'!C17 -> 0
A31: Mar | B31: ='Saisie mensuelle'!D16 -> 0 | C31: ='Saisie mensuelle'!D17 -> 0
A32: Avr | B32: ='Saisie mensuelle'!E16 -> 0 | C32: ='Saisie mensuelle'!E17 -> 0
A33: Mai | B33: ='Saisie mensuelle'!F16 -> 0 | C33: ='Saisie mensuelle'!F17 -> 0
A34: Jui | B34: ='Saisie mensuelle'!G16 -> 0 | C34: ='Saisie mensuelle'!G17 -> 0
A35: Jul | B35: ='Saisie mensuelle'!H16 -> 0 | C35: ='Saisie mensuelle'!H17 -> 0
A36: Aoû | B36: ='Saisie mensuelle'!I16 -> 0 | C36: ='Saisie mensuelle'!I17 -> 0
A37: Sep | B37: ='Saisie mensuelle'!J16 -> 0 | C37: ='Saisie mensuelle'!J17 -> 0
A38: Oct | B38: ='Saisie mensuelle'!K16 -> 0 | C38: ='Saisie mensuelle'!K17 -> 0
A39: Nov | B39: ='Saisie mensuelle'!L16 -> 0 | C39: ='Saisie mensuelle'!L17 -> 0
A40: Déc | B40: ='Saisie mensuelle'!M16 -> 0 | C40: ='Saisie mensuelle'!M17 -> 0

Sheet Retraitements
A1: EBITDA NORMALISÉ — RETRAITEMENTS
A2: Neutralisez les éléments non récurrents pour obtenir votre EBITDA réel
A4: L'EBITDA normalisé neutralise les charges et produits exceptionnels ou non représentatifs de l'activité courante. Exemples : prime exceptionnelle dirigeant, loyer anormal vs marché, frais de restructuration, charges non récurrentes. C'est l'EBITDA que regardent les banquiers et repreneurs pour valoriser votre entreprise.
A8: POSTE | B8: Jan | C8: Fév | D8: Mar | E8: Avr | F8: Mai | G8: Jui | H8: Jul | I8: Aoû | J8: Sep | K8: Oct | L8: Nov | M8: Déc | N8: TOTAL
A9: EBITDA brut (tiré de Saisie mensuelle) | B9: ='Saisie mensuelle'!B16 -> 0 | C9: ='Saisie mensuelle'!C16 -> 0 | D9: ='Saisie mensuelle'!D16 -> 0 | E9: ='Saisie mensuelle'!E16 -> 0 | F9: ='Saisie mensuelle'!F16 -> 0 | G9: ='Saisie mensuelle'!G16 -> 0 | H9: ='Saisie mensuelle'!H16 -> 0 | I9: ='Saisie mensuelle'!I16 -> 0 | ... N9: ='Saisie mensuelle'!N16 -> 0
A10: ▶ RETRAITEMENTS [saisir en positif = charge à neutraliser / négatif = produit à neutraliser]
A11: Rémunération dirigeant hors marché (€) | B11: 0 | C11: 0 | D11: 0 | E11: 0 | F11: 0 | G11: 0 | H11: 0 | I11: 0 | J11: 0 | K11: 0 | L11: 0 | M11: 0 | N11: =SUM(B11:M11) -> 0
A12: Loyer anormal vs marché (€) | B12: 0 | C12: 0 | D12: 0 | E12: 0 | F12: 0 | G12: 0 | H12: 0 | I12: 0 | J12: 0 | K12: 0 | L12: 0 | M12: 0 | N12: =SUM(B12:M12) -> 0
A13: Charges non récurrentes (restructuration, etc.) (€) | B13: 0 | C13: 0 | D13: 0 | E13: 0 | F13: 0 | G13: 0 | H13: 0 | I13: 0 | J13: 0 | K13: 0 | L13: 0 | M13: 0 | N13: =SUM(B13:M13) -> 0
A14: Autres retraitements (€) | B14: 0 | C14: 0 | D14: 0 | E14: 0 | F14: 0 | G14: 0 | H14: 0 | I14: 0 | J14: 0 | K14: 0 | L14: 0 | M14: 0 | N14: =SUM(B14:M14) -> 0
A15: Total retraitements (€) | B15: =B11+B12+B13+B14 -> 0 | C15: =C11+C12+C13+C14 -> 0 | D15: =D11+D12+D13+D14 -> 0 | E15: =E11+E12+E13+E14 -> 0 | F15: =F11+F12+F13+F14 -> 0 | G15: =G11+G12+G13+G14 -> 0 | H15: =H11+H12+H13+H14 -> 0 | I15: =I11+I12+I13+I14 -> 0 | ... M15: =M11+M12+M13+M14 -> 0 | N15: =SUM(B15:M15) -> 0
A16: EBITDA NORMALISÉ (€) | B16: =B9+B15 -> 0 | C16: =C9+C15 -> 0 | D16: =D9+D15 -> 0 | E16: =E9+E15 -> 0 | F16: =F9+F15 -> 0 | G16: =G9+G15 -> 0 | H16: =H9+H15 -> 0 | I16: =I9+I15 -> 0 | ... N16: =N9+N15 -> 0
A17: Marge EBITDA normalisée (%) | B17: =IF('Saisie mensuelle'!B6=0,0,B16/'Saisie mensuelle'!B6) -> 0 | C17: =IF('Saisie mensuelle'!C6=0,0,C16/'Saisie mensuelle'!C6) -> 0 | D17: =IF('Saisie mensuelle'!D6=0,0,D16/'Saisie mensuelle'!D6) -> 0 | E17: =IF('Saisie mensuelle'!E6=0,0,E16/'Saisie mensuelle'!E6) -> 0 | F17: =IF('Saisie mensuelle'!F6=0,0,F16/'Saisie mensuelle'!F6) -> 0 | G17: =IF('Saisie mensuelle'!G6=0,0,G16/'Saisie mensuelle'!G6) -> 0 | H17: =IF('Saisie mensuelle'!H6=0,0,H16/'Saisie mensuelle'!H6) -> 0 | I17: =IF('Saisie mensuelle'!I6=0,0,I16/'Saisie mensuelle'!I6) -> 0 | ... N17: =IF('Saisie mensuelle'!N6=0,0,N16/'Saisie mensuelle'!N6) -> 0
A20: ▶ BENCHMARKS SECTORIELS (Banque de France / INSEE)
A21: Services B2B | B21: 12% - 18% | G21: Cible idéale > 15%
A22: Commerce / Distribution | B22: 5% - 10% | G22: Cible idéale > 8%
A23: BTP / Construction | B23: 6% - 12% | G23: Cible idéale > 9%
A24: SaaS / Tech | B24: 15% - 30% | G24: Cible idéale > 20%
A27: Sources : Banque de France — Statistiques sectorielles PME 2024 | FinSight — finsight.zineinsight.com
