Workbook

Sheet Dashboard 90J
A2: DASHBOARD TRÉSORERIE 90 JOURS — VUE DIRIGEANT
A5: KPIs TRÉSORERIE — VUE 90 JOURS
A6: SOLDE INITIAL | C6: SOLDE FIN J90 | E6: FLUX NET 90J
A7: =Config!$B$12 -> 80000 | C7: ='Flux 13 Semaines'!N24 -> 134600 | E7: ='Flux 13 Semaines'!O23 -> 54600
A8: Au démarrage J0 | C8: Fin de semaine 13 | E8: Encaiss. − Décaiss.
A11: TOTAL ENCAISSÉ | C11: TOTAL DÉCAISSÉ | E11: SEMAINES EN ALERTE
A12: ='Flux 13 Semaines'!O10 -> 234000 | C12: ='Flux 13 Semaines'!O15+'Flux 13 Semaines'!O21 -> 179400 | E12: =COUNTIF('Flux 13 Semaines'!B25:N25,"🚨 DANGER")+COUNTIF('Flux 13 Semaines'!B25:N25,"⚠️ Vigilance") -> 0
A13: Sur 90 jours | C13: Fixes + Variables | E13: Nb semaines critiques
A17: SYNTHÈSE PAR MOIS
A18: Période | B18: Encaissements | C18: Décaissements | D18: Flux net | E18: Solde fin période | F18: Statut
A19: Mois 1 — S1 à S4 | B19: =SUM('Flux 13 Semaines'!B10:E10) -> 72000 | C19: =SUM('Flux 13 Semaines'!B15:E15)+SUM('Flux 13 Semaines'!B21:E21) -> 55200 | D19: =SUM('Flux 13 Semaines'!B23:E23) -> 16800 | E19: ='Flux 13 Semaines'!E24 -> 96800 | F19: =IF('Flux 13 Semaines'!E24<Config!$B$13,"🚨 DANGER",IF('Flux 13 Semaines'!E24<Config!$B$14,"⚠️ Vigilance",IF('Flux 13 Semaines'!E24<Config!$B$15,"🔔 Surveiller","✅ OK"))) -> ✅ OK
A20: Mois 2 — S5 à S9 | B20: =SUM('Flux 13 Semaines'!F10:J10) -> 90000 | C20: =SUM('Flux 13 Semaines'!F15:J15)+SUM('Flux 13 Semaines'!F21:J21) -> 69000 | D20: =SUM('Flux 13 Semaines'!F23:J23) -> 21000 | E20: ='Flux 13 Semaines'!J24 -> 117800 | F20: =IF('Flux 13 Semaines'!J24<Config!$B$13,"🚨 DANGER",IF('Flux 13 Semaines'!J24<Config!$B$14,"⚠️ Vigilance",IF('Flux 13 Semaines'!J24<Config!$B$15,"🔔 Surveiller","✅ OK"))) -> ✅ OK
A21: Mois 3 — S10 à S13 | B21: =SUM('Flux 13 Semaines'!K10:N10) -> 72000 | C21: =SUM('Flux 13 Semaines'!K15:N15)+SUM('Flux 13 Semaines'!K21:N21) -> 55200 | D21: =SUM('Flux 13 Semaines'!K23:N23) -> 16800 | E21: ='Flux 13 Semaines'!N24 -> 134600 | F21: =IF('Flux 13 Semaines'!N24<Config!$B$13,"🚨 DANGER",IF('Flux 13 Semaines'!N24<Config!$B$14,"⚠️ Vigilance",IF('Flux 13 Semaines'!N24<Config!$B$15,"🔔 Surveiller","✅ OK"))) -> ✅ OK
A23: SCÉNARIOS À 90 JOURS
A24: Scénario | B24: Hypothèse | C24: Flux net 90j | D24: Solde final | E24: vs Seuil confort
A25: Base | B25: Flux actuels | C25: ='Flux 13 Semaines'!O23 -> 54600 | D25: ='Flux 13 Semaines'!N24 -> 134600 | E25: =D25-Config!$B$15 -> 84600
A26: Pessimiste (−20%) | B26: Encaissements ×0.8 | C26: ='Flux 13 Semaines'!O10*0.8-'Flux 13 Semaines'!O15-'Flux 13 Semaines'!O21 -> 7800 | D26: =Config!$B$12+('Flux 13 Semaines'!O10*0.8-'Flux 13 Semaines'!O15-'Flux 13 Semaines'!O21) -> 87800 | E26: =D26-Config!$B$15 -> 37800
A27: Optimiste (+15%) | B27: Encaissements ×1.15 | C27: ='Flux 13 Semaines'!O10*1.15-'Flux 13 Semaines'!O15-'Flux 13 Semaines'!O21 -> 89700 | D27: =Config!$B$12+('Flux 13 Semaines'!O10*1.15-'Flux 13 Semaines'!O15-'Flux 13 Semaines'!O21) -> 169700 | E27: =D27-Config!$B$15 -> 119700
A30: 📌 GUIDE D'UTILISATION 1. 'Config' : renseignez le solde initial et vos seuils d'alerte. 2. 'Flux 13 Semaines' : saisissez vos encaissements et décaissements semaine par semaine. 3. Ce Dashboard se recalcule automatiquement — 3 scénarios inclus. 4. Les alertes 🚨⚠️🔔 s'activent automatiquement selon vos seuils. 💡 FinSight — finsight.zineinsight.com

Sheet Config
A2: PRÉVISIONNEL TRÉSORERIE 90 JOURS — CONFIGURATION
A4: FinSight · Pilotage financier PME · finsight.zineinsight.com
A6: 🏢 ENTREPRISE & PÉRIODE
A7: Nom de l'entreprise | B7: Ma PME SAS
A8: Date de début (S1) | C8: Ex : 12/05/2026
A9: Secteur | B9: Services | C9: Services / Commerce / Industrie
A11: 🏦 TRÉSORERIE DE DÉPART
A12: Solde trésorerie initial (J0) | B12: 80000 | C12: Solde réel au démarrage
A13: Seuil alerte rouge | B13: 15000 | C13: 🚨 Danger immédiat
A14: Seuil alerte orange | B14: 30000 | C14: ⚠️ Zone de vigilance
A15: Seuil confort | B15: 50000 | C15: ✅ Zone de confort
A17: 📊 HYPOTHÈSES HEBDOMADAIRES TYPES
A18: Encaissements clients moyens / semaine | B18: 18000 | C18: Base de calcul scénario
A19: Décaissements fixes / semaine | B19: 12000 | C19: Salaires + loyer + charges
A20: Décaissements variables / semaine | B20: 3000 | C20: Fournisseurs, divers
A23: ⚡ Cellules jaunes = INPUTS à modifier. 📅 Saisissez semaine par semaine dans 'Flux 13 Semaines'. 🎯 Dashboard et Alertes 30/60/90j se calculent automatiquement.

Sheet Flux 13 Semaines
A2: FLUX DE TRÉSORERIE — 13 SEMAINES (90 JOURS)
A5: RUBRIQUE | B5: S1 | C5: S2 | D5: S3 | E5: S4 | F5: S5 | G5: S6 | H5: S7 | I5: S8 | J5: S9 | K5: S10 | L5: S11 | M5: S12 | N5: S13 | O5: TOTAL | P5: MOY/SEM
B6: ◀── MOIS 1 (J1-J28) ──▶ | F6: ◀──── MOIS 2 (J29-J63) ────▶ | K6: ◀── MOIS 3 (J64-J90) ──▶
A7: ENCAISSEMENTS
A8: Encaissements clients | B8: =Config!$B$18 -> 18000 | C8: =Config!$B$18 -> 18000 | D8: =Config!$B$18 -> 18000 | E8: =Config!$B$18 -> 18000 | F8: =Config!$B$18 -> 18000 | G8: =Config!$B$18 -> 18000 | H8: =Config!$B$18 -> 18000 | I8: =Config!$B$18 -> 18000 | ... N8: =Config!$B$18 -> 18000 | O8: =SUM(B8:N8) -> 234000 | P8: =O8/13 -> 18000
A9: Autres encaissements (subventions, TVA…) | B9: 0 | C9: 0 | D9: 0 | E9: 0 | F9: 0 | G9: 0 | H9: 0 | I9: 0 | J9: 0 | K9: 0 | L9: 0 | M9: 0 | N9: 0 | O9: =SUM(B9:N9) -> 0 | P9: =O9/13 -> 0
A10: ▶ TOTAL ENCAISSEMENTS | B10: =B8+B9 -> 18000 | C10: =C8+C9 -> 18000 | D10: =D8+D9 -> 18000 | E10: =E8+E9 -> 18000 | F10: =F8+F9 -> 18000 | G10: =G8+G9 -> 18000 | H10: =H8+H9 -> 18000 | I10: =I8+I9 -> 18000 | ... N10: =N8+N9 -> 18000 | O10: =SUM(B10:N10) -> 234000 | P10: =O10/13 -> 18000
A11: DÉCAISSEMENTS FIXES
A12: (-) Charges de personnel | B12: =Config!$B$19*0.6 -> 7200 | C12: =Config!$B$19*0.6 -> 7200 | D12: =Config!$B$19*0.6 -> 7200 | E12: =Config!$B$19*0.6 -> 7200 | F12: =Config!$B$19*0.6 -> 7200 | G12: =Config!$B$19*0.6 -> 7200 | H12: =Config!$B$19*0.6 -> 7200 | I12: =Config!$B$19*0.6 -> 7200 | ... N12: =Config!$B$19*0.6 -> 7200 | O12: =SUM(B12:N12) -> 93600 | P12: =O12/13 -> 7200
A13: (-) Loyer & charges locatives | B13: =Config!$B$19*0.2 -> 2400 | C13: =Config!$B$19*0.2 -> 2400 | D13: =Config!$B$19*0.2 -> 2400 | E13: =Config!$B$19*0.2 -> 2400 | F13: =Config!$B$19*0.2 -> 2400 | G13: =Config!$B$19*0.2 -> 2400 | H13: =Config!$B$19*0.2 -> 2400 | I13: =Config!$B$19*0.2 -> 2400 | ... N13: =Config!$B$19*0.2 -> 2400 | O13: =SUM(B13:N13) -> 31200 | P13: =O13/13 -> 2400
A14: (-) Autres charges fixes | B14: =Config!$B$19*0.2 -> 2400 | C14: =Config!$B$19*0.2 -> 2400 | D14: =Config!$B$19*0.2 -> 2400 | E14: =Config!$B$19*0.2 -> 2400 | F14: =Config!$B$19*0.2 -> 2400 | G14: =Config!$B$19*0.2 -> 2400 | H14: =Config!$B$19*0.2 -> 2400 | I14: =Config!$B$19*0.2 -> 2400 | ... N14: =Config!$B$19*0.2 -> 2400 | O14: =SUM(B14:N14) -> 31200 | P14: =O14/13 -> 2400
A15: ▶ TOTAL FIXES | B15: =B12+B13+B14 -> 12000 | C15: =C12+C13+C14 -> 12000 | D15: =D12+D13+D14 -> 12000 | E15: =E12+E13+E14 -> 12000 | F15: =F12+F13+F14 -> 12000 | G15: =G12+G13+G14 -> 12000 | H15: =H12+H13+H14 -> 12000 | I15: =I12+I13+I14 -> 12000 | ... N15: =N12+N13+N14 -> 12000 | O15: =SUM(B15:N15) -> 156000 | P15: =O15/13 -> 12000
A16: DÉCAISSEMENTS VARIABLES
A17: (-) Paiements fournisseurs | B17: =Config!$B$20*0.6 -> 1800 | C17: =Config!$B$20*0.6 -> 1800 | D17: =Config!$B$20*0.6 -> 1800 | E17: =Config!$B$20*0.6 -> 1800 | F17: =Config!$B$20*0.6 -> 1800 | G17: =Config!$B$20*0.6 -> 1800 | H17: =Config!$B$20*0.6 -> 1800 | I17: =Config!$B$20*0.6 -> 1800 | ... N17: =Config!$B$20*0.6 -> 1800 | O17: =SUM(B17:N17) -> 23400 | P17: =O17/13 -> 1800
A18: (-) TVA à décaisser (mensuel S4/S9/S13) | B18: 0 | C18: 0 | D18: 0 | E18: 0 | F18: 0 | G18: 0 | H18: 0 | I18: 0 | J18: 0 | K18: 0 | L18: 0 | M18: 0 | N18: 0 | O18: =SUM(B18:N18) -> 0 | P18: =O18/13 -> 0
A19: (-) Remboursements d'emprunts | B19: 0 | C19: 0 | D19: 0 | E19: 0 | F19: 0 | G19: 0 | H19: 0 | I19: 0 | J19: 0 | K19: 0 | L19: 0 | M19: 0 | N19: 0 | O19: =SUM(B19:N19) -> 0 | P19: =O19/13 -> 0
A20: (-) Investissements ponctuels | B20: 0 | C20: 0 | D20: 0 | E20: 0 | F20: 0 | G20: 0 | H20: 0 | I20: 0 | J20: 0 | K20: 0 | L20: 0 | M20: 0 | N20: 0 | O20: =SUM(B20:N20) -> 0 | P20: =O20/13 -> 0
A21: ▶ TOTAL VARIABLES | B21: =B17+B18+B19+B20 -> 1800 | C21: =C17+C18+C19+C20 -> 1800 | D21: =D17+D18+D19+D20 -> 1800 | E21: =E17+E18+E19+E20 -> 1800 | F21: =F17+F18+F19+F20 -> 1800 | G21: =G17+G18+G19+G20 -> 1800 | H21: =H17+H18+H19+H20 -> 1800 | I21: =I17+I18+I19+I20 -> 1800 | ... N21: =N17+N18+N19+N20 -> 1800 | O21: =SUM(B21:N21) -> 23400 | P21: =O21/13 -> 1800
A22: SYNTHÈSE HEBDOMADAIRE
A23: ▶ FLUX NET DE LA SEMAINE | B23: =B10-B15-B21 -> 4200 | C23: =C10-C15-C21 -> 4200 | D23: =D10-D15-D21 -> 4200 | E23: =E10-E15-E21 -> 4200 | F23: =F10-F15-F21 -> 4200 | G23: =G10-G15-G21 -> 4200 | H23: =H10-H15-H21 -> 4200 | I23: =I10-I15-I21 -> 4200 | ... N23: =N10-N15-N21 -> 4200 | O23: =SUM(B23:N23) -> 54600 | P23: =O23/13 -> 4200
A24: ▶ SOLDE EN FIN DE SEMAINE | B24: =Config!$B$12+B23 -> 84200 | C24: =B24+C23 -> 88400 | D24: =C24+D23 -> 92600 | E24: =D24+E23 -> 96800 | F24: =E24+F23 -> 101000 | G24: =F24+G23 -> 105200 | H24: =G24+H23 -> 109400 | I24: =H24+I23 -> 113600 | J24: =I24+J23 -> 117800 | ... N24: =M24+N23 -> 134600 | O24: =N24 -> 134600
A25: Alerte niveau trésorerie | B25: =IF(B24<Config!$B$13,"🚨 DANGER",IF(B24<Config!$B$14,"⚠️ Vigilance",IF(B24<Config!$B$15,"🔔 Surveiller","✅ OK"))) -> ✅ OK | C25: =IF(C24<Config!$B$13,"🚨 DANGER",IF(C24<Config!$B$14,"⚠️ Vigilance",IF(C24<Config!$B$15,"🔔 Surveiller","✅ OK"))) -> ✅ OK | D25: =IF(D24<Config!$B$13,"🚨 DANGER",IF(D24<Config!$B$14,"⚠️ Vigilance",IF(D24<Config!$B$15,"🔔 Surveiller","✅ OK"))) -> ✅ OK | E25: =IF(E24<Config!$B$13,"🚨 DANGER",IF(E24<Config!$B$14,"⚠️ Vigilance",IF(E24<Config!$B$15,"🔔 Surveiller","✅ OK"))) -> ✅ OK | F25: =IF(F24<Config!$B$13,"🚨 DANGER",IF(F24<Config!$B$14,"⚠️ Vigilance",IF(F24<Config!$B$15,"🔔 Surveiller","✅ OK"))) -> ✅ OK | G25: =IF(G24<Config!$B$13,"🚨 DANGER",IF(G24<Config!$B$14,"⚠️ Vigilance",IF(G24<Config!$B$15,"🔔 Surveiller","✅ OK"))) -> ✅ OK | H25: =IF(H24<Config!$B$13,"🚨 DANGER",IF(H24<Config!$B$14,"⚠️ Vigilance",IF(H24<Config!$B$15,"🔔 Surveiller","✅ OK"))) -> ✅ OK | I25: =IF(I24<Config!$B$13,"🚨 DANGER",IF(I24<Config!$B$14,"⚠️ Vigilance",IF(I24<Config!$B$15,"🔔 Surveiller","✅ OK"))) -> ✅ OK | ... N25: =IF(N24<Config!$B$13,"🚨 DANGER",IF(N24<Config!$B$14,"⚠️ Vigilance",IF(N24<Config!$B$15,"🔔 Surveiller","✅ OK"))) -> ✅ OK
